astdoc/__init__.py
astdoc/ast.py
astdoc/doc.py
astdoc/markdown.py
astdoc/node.py
astdoc/object.py
astdoc/py.typed
astdoc/utils.py
astdoc-1.3.2.dist-info/WHEEL
astdoc-1.3.2.dist-info/METADATA
astdoc-1.3.2.dist-info/RECORD
