Metadata-Version: 2.3
Name: astdoc
Version: 1.3.2
Summary: A lightweight Python library for parsing AST and extracting docstring information. Automatically generate documentation from Python source code by analyzing abstract syntax trees and docstrings.
Keywords: ast,documentation,docstring,parser,code-analysis,documentation-generator,python,static-analysis,code-documentation,api-documentation,google-style,numpy-style,sphinx,mkdocs
Author: daizutabi
Author-email: daizutabi <daizutabi@gmail.com>
License: MIT License
Classifier: Development Status :: 5 - Production/Stable
Classifier: Programming Language :: Python
Classifier: Programming Language :: Python :: 3.10
Classifier: Programming Language :: Python :: 3.11
Classifier: Programming Language :: Python :: 3.12
Classifier: Programming Language :: Python :: 3.13
Classifier: Programming Language :: Python :: 3.14
Classifier: Topic :: Documentation
Classifier: Topic :: Software Development :: Documentation
Classifier: Topic :: Software Development :: Libraries :: Python Modules
Classifier: Topic :: Text Processing :: Markup :: Markdown
Classifier: Intended Audience :: Developers
Classifier: Framework :: MkDocs
Classifier: Framework :: Sphinx
Requires-Python: >=3.10
Project-URL: Changelog, https://github.com/daizutabi/astdoc/blob/main/CHANGELOG.md
Project-URL: Documentation, https://daizutabi.github.io/astdoc/
Project-URL: Issues, https://github.com/daizutabi/astdoc/issues
Project-URL: Source, https://github.com/daizutabi/astdoc
